Metadata-Version: 2.1
Name: conan-sword-and-sorcery
Version: 0.0.dev133
Summary: Utilities to work with conan.io stuf
Home-page: https://gitlab.com/jgsogo/conan-sword-and-sorcery
Author: jgsogo
Author-email: jgsogo@gmail.com
License: MIT
Keywords: conan,C/C++,package,libraries,developer,manager,dependency,tool,c,c++,cpp
Platform: UNKNOWN
Classifier: Development Status :: 1 - Planning
Classifier: Intended Audience :: Developers
Classifier: Topic :: Software Development :: Build Tools
Classifier: License :: OSI Approved :: MIT License
Classifier: Programming Language :: Python :: 2
Classifier: Programming Language :: Python :: 2.7
Classifier: Programming Language :: Python :: 3
Provides-Extra: test
